jf_util/__init__.py
jf_util-0.1.dist-info/METADATA
jf_util-0.1.dist-info/WHEEL
jf_util-0.1.dist-info/top_level.txt
jf_util-0.1.dist-info/RECORD
