Metadata-Version: 2.1
Name: jf-util
Version: 0.1
Summary: Utility package by James Fang
Home-page: https://github.com/jthefang/jf_util
Author: James Fang
Author-email: jtotheamesfang@gmail.com
License: MIT
Platform: UNKNOWN
